ghreports/__init__.py
ghreports/__main__.py
ghreports/cli.py
ghreports/config.py
ghreports/generator.py
ghreports/main.py
ghreports/py.typed
ghreports/reader.py
ghreports/report.py
ghreports/schema.json
ghreports/templates/search.graphql
ghreports/templates/template.md
ghreports-0.1.2.dist-info/LICENSE
ghreports-0.1.2.dist-info/METADATA
ghreports-0.1.2.dist-info/WHEEL
ghreports-0.1.2.dist-info/entry_points.txt
ghreports-0.1.2.dist-info/RECORD
