Metadata-Version: 2.3
Name: ghreports
Version: 0.1.2
Summary: GitHub Report tool
License: BSD 3 Clause
Author: Ivan Ogasawara
Author-email: ivan.ogasawara@gmail.com
Requires-Python: >=3.9,<4
Classifier: License :: Other/Proprietary License
Classifier: Programming Language :: Python :: 3
Classifier: Programming Language :: Python :: 3.9
Classifier: Programming Language :: Python :: 3.10
Classifier: Programming Language :: Python :: 3.11
Classifier: Programming Language :: Python :: 3.12
Classifier: Programming Language :: Python :: 3.13
Requires-Dist: Jinja2 (>=3)
Requires-Dist: aiohttp (>=3.7.1)
Requires-Dist: atpublic (>=4.0)
Requires-Dist: gql (>=3)
Requires-Dist: pandas (>=1.4.2)
Requires-Dist: pandoc (>=2.1)
Requires-Dist: python-dotenv (>=0.21.1)
Requires-Dist: pyyaml (>=5.4)
Requires-Dist: requests (>=2.23)
Requires-Dist: tabulate (>=0.8.9)
Requires-Dist: typer (>=0.16.0,<0.17.0)
Requires-Dist: types-pyyaml (>=6.0.12.20250516,<7.0.0.0)
Requires-Dist: websockets (>=8.1)
